m3_gar_client/__init__.py
m3_gar_client/apps.py
m3_gar_client/const.py
m3_gar_client/data.py
m3_gar_client/ui.py
m3_gar_client/utils.py
m3_gar_client/backends/__init__.py
m3_gar_client/backends/base.py
m3_gar_client/backends/m3_rest_gar/__init__.py
m3_gar_client/backends/m3_rest_gar/base.py
m3_gar_client/backends/m3_rest_gar/server.py
m3_gar_client/backends/m3_rest_gar/utils.py
m3_gar_client/backends/m3_rest_gar/proxy/__init__.py
m3_gar_client/backends/m3_rest_gar/proxy/actions.py
m3_gar_client/backends/m3_rest_gar/proxy_rest/__init__.py
m3_gar_client/backends/m3_rest_gar/proxy_rest/authentication.py
m3_gar_client/backends/m3_rest_gar/proxy_rest/const.py
m3_gar_client/backends/m3_rest_gar/proxy_rest/urls.py
m3_gar_client/backends/m3_rest_gar/proxy_rest/views.py
m3_gar_client/management/__init__.py
m3_gar_client/management/commands/__init__.py
m3_gar_client/management/commands/clear_gar_cache.py
m3_gar_client/static/m3/js/gar/AddressPanel.js
m3_gar_client/static/m3/js/gar/AddressPanelPatch.js
m3_gar_client-1.4.0.dist-info/licenses/LICENSE
m3_gar_client-1.4.0.dist-info/METADATA
m3_gar_client-1.4.0.dist-info/WHEEL
m3_gar_client-1.4.0.dist-info/dependency_links.txt
m3_gar_client-1.4.0.dist-info/top_level.txt
m3_gar_client-1.4.0.dist-info/RECORD
