Metadata-Version: 2.4
Name: m3-gar-client
Version: 1.4.0
Summary: UI клиент для сервера ГАР m3-rest-gar
Home-page: https://stash.bars-open.ru/projects/M3/repos/m3-gar-client
Author: BARS Group
Author-email: bars@bars-open.ru
License: MIT
Classifier: Intended Audience :: Developers
Classifier: Environment :: Web Environment
Classifier: Natural Language :: Russian
Classifier: Operating System :: OS Independent
Classifier: Programming Language :: Python
Classifier: Programming Language :: Python :: 3.7
Classifier: Programming Language :: Python :: 3.8
Classifier: Programming Language :: Python :: 3.9
Classifier: Programming Language :: Python :: 3.10
Classifier: Programming Language :: Python :: 3.11
Classifier: Programming Language :: Python :: 3.12
Classifier: Development Status :: 5 - Production/Stable
Classifier: Framework :: Django :: 2.2
Classifier: Framework :: Django :: 3.1
Classifier: Framework :: Django :: 3.2
Classifier: Framework :: Django :: 4.0
Classifier: Framework :: Django :: 4.1
Classifier: Framework :: Django :: 4.2
Classifier: Framework :: Django :: 5.0
Requires-Python: >=3.6
License-File: LICENSE
Requires-Dist: requests<3,>=2
Requires-Dist: django<5.1,>=2.2
Requires-Dist: m3-gar-constants>=1.0.4
Provides-Extra: oauth2
Requires-Dist: oauthlib<3.3,>=2; extra == "oauth2"
Requires-Dist: requests-oauthlib<=1.3.1; extra == "oauth2"
Provides-Extra: m3
Requires-Dist: m3-core<4,>=2.2.16; extra == "m3"
Requires-Dist: m3-ui<3,>=2.0.8; extra == "m3"
Provides-Extra: rest
Requires-Dist: djangorestframework; extra == "rest"
Dynamic: author
Dynamic: author-email
Dynamic: classifier
Dynamic: description
Dynamic: description-content-type
Dynamic: home-page
Dynamic: license
Dynamic: license-file
Dynamic: provides-extra
Dynamic: requires-dist
Dynamic: requires-python
Dynamic: summary
